x_mlps_pytorch/__init__.py
x_mlps_pytorch/activations.py
x_mlps_pytorch/ensemble.py
x_mlps_pytorch/ff.py
x_mlps_pytorch/ff_with_latent.py
x_mlps_pytorch/grouped_ff.py
x_mlps_pytorch/grouped_mlp.py
x_mlps_pytorch/grouped_nff.py
x_mlps_pytorch/mlp.py
x_mlps_pytorch/mlp_with_latent.py
x_mlps_pytorch/nff.py
x_mlps_pytorch/noisable.py
x_mlps_pytorch/normed_mlp.py
x_mlps_pytorch/norms.py
x_mlps_pytorch/residual_normed_mlp.py
x_mlps_pytorch-0.1.32.dist-info/METADATA
x_mlps_pytorch-0.1.32.dist-info/WHEEL
x_mlps_pytorch-0.1.32.dist-info/licenses/LICENSE
x_mlps_pytorch-0.1.32.dist-info/RECORD
