Metadata-Version: 2.4
Name: x-mlps-pytorch
Version: 0.1.32
Summary: A collection of MLPs / Feedforwards for Pytorch
Project-URL: Homepage, https://pypi.org/project/x-mlps-pytorch/
Project-URL: Repository, https://github.com/lucidrains/x-mlps
Author-email: Phil Wang <lucidrains@gmail.com>
License: MIT License
License-File: LICENSE
Keywords: artificial intelligence,deep learning,feedforwards,mlps
Classifier: Development Status :: 4 - Beta
Classifier: Intended Audience :: Developers
Classifier: License :: OSI Approved :: MIT License
Classifier: Programming Language :: Python :: 3.8
Classifier: Topic :: Scientific/Engineering :: Artificial Intelligence
Requires-Python: >=3.8
Requires-Dist: einops>=0.8.0
Requires-Dist: torch>=2.4
Provides-Extra: test
Requires-Dist: pytest; extra == 'test'
